montybase/__init__.py
montybase-0.1.6.dist-info/LICENSE
montybase-0.1.6.dist-info/METADATA
montybase-0.1.6.dist-info/WHEEL
montybase-0.1.6.dist-info/RECORD
