Metadata-Version: 2.1
Name: montybase
Version: 0.1.6
Summary: Simple, Python-based, NoSQL, document, database inspired by Firebase Firestore.
Home-page: https://github.com/amooo-ooo/montybase
License: MIT
Author: Amor Budiyanto
Author-email: amor.budiyanto@gmail.com
Requires-Python: >=3.6
Classifier: License :: OSI Approved :: MIT License
Classifier: Programming Language :: Python :: 3
Classifier: Programming Language :: Python :: 3.6
Classifier: Programming Language :: Python :: 3.7
Classifier: Programming Language :: Python :: 3.8
Classifier: Programming Language :: Python :: 3.9
Classifier: Programming Language :: Python :: 3.10
Classifier: Programming Language :: Python :: 3.11
Classifier: Programming Language :: Python :: 3.12
Provides-Extra: dev
Requires-Dist: cryptography (>=3.0.0,<4.0.0)
Requires-Dist: flask (>=2.0.0,<3.0.0)
Requires-Dist: flask_cors (>=3.0.0,<4.0.0)
Requires-Dist: nanoid (>=2.0.0,<3.0.0)
Requires-Dist: requests (>=2.0.0,<3.0.0)
